magnus/__init__.py
magnus/catalog.py
magnus/cli.py
magnus/context.py
magnus/datastore.py
magnus/defaults.py
magnus/entrypoints.py
magnus/exceptions.py
magnus/executor.py
magnus/experiment_tracker.py
magnus/extensions/__init__.py
magnus/extensions/catalog/__init__.py
magnus/extensions/catalog/file_system/__init__.py
magnus/extensions/catalog/file_system/implementation.py
magnus/extensions/catalog/k8s_pvc/__init__.py
magnus/extensions/catalog/k8s_pvc/implementation.py
magnus/extensions/catalog/k8s_pvc/integration.py
magnus/extensions/executor/__init__.py
magnus/extensions/executor/argo/__init__.py
magnus/extensions/executor/argo/implementation.py
magnus/extensions/executor/argo/specification.yaml
magnus/extensions/executor/k8s_job/__init__.py
magnus/extensions/executor/k8s_job/implementation_FF.py
magnus/extensions/executor/k8s_job/integration_FF.py
magnus/extensions/executor/local/__init__.py
magnus/extensions/executor/local/implementation.py
magnus/extensions/executor/local_container/__init__.py
magnus/extensions/executor/local_container/implementation.py
magnus/extensions/executor/mocked/__init__.py
magnus/extensions/executor/mocked/implementation.py
magnus/extensions/experiment_tracker/__init__.py
magnus/extensions/experiment_tracker/mlflow/__init__.py
magnus/extensions/experiment_tracker/mlflow/implementation.py
magnus/extensions/nodes.py
magnus/extensions/run_log_store/__init__.py
magnus/extensions/run_log_store/chunked_file_system/__init__.py
magnus/extensions/run_log_store/chunked_file_system/implementation.py
magnus/extensions/run_log_store/chunked_k8s_pvc/__init__.py
magnus/extensions/run_log_store/chunked_k8s_pvc/implementation.py
magnus/extensions/run_log_store/chunked_k8s_pvc/integration.py
magnus/extensions/run_log_store/db/implementation_FF.py
magnus/extensions/run_log_store/db/integration_FF.py
magnus/extensions/run_log_store/file_system/__init__.py
magnus/extensions/run_log_store/file_system/implementation.py
magnus-0.5.1.dist-info/LICENSE
magnus-0.5.1.dist-info/METADATA
magnus-0.5.1.dist-info/WHEEL
magnus-0.5.1.dist-info/entry_points.txt
magnus-0.5.1.dist-info/RECORD
