Metadata-Version: 2.1
Name: magnus
Version: 0.5.1
Summary: A Compute agnostic pipelining software
Home-page: https://github.com/AstraZeneca/magnus-core
License: Apache-2.0
Author: Vijay Vammi
Author-email: mesanthu@gmail.com
Requires-Python: >=3.8,<3.13
Classifier: License :: OSI Approved :: Apache Software License
Classifier: Programming Language :: Python :: 3
Classifier: Programming Language :: Python :: 3.8
Classifier: Programming Language :: Python :: 3.9
Classifier: Programming Language :: Python :: 3.10
Classifier: Programming Language :: Python :: 3.11
Classifier: Programming Language :: Python :: 3.12
Provides-Extra: database
Provides-Extra: docker
Provides-Extra: mlflow
Provides-Extra: notebook
Requires-Dist: click
Requires-Dist: click-plugins (>=1.1.1,<2.0.0)
Requires-Dist: docker ; extra == "docker"
Requires-Dist: mlflow-skinny ; extra == "mlflow"
Requires-Dist: ploomber-engine (>=0.0.31,<0.0.32) ; extra == "notebook"
Requires-Dist: pydantic (>=2.5,<3.0)
Requires-Dist: rich (>=13.5.2,<14.0.0)
Requires-Dist: ruamel.yaml
Requires-Dist: ruamel.yaml.clib
Requires-Dist: sqlalchemy ; extra == "database"
Requires-Dist: stevedore (>=3.5.0,<4.0.0)
Requires-Dist: typing-extensions ; python_version < "3.8"
Project-URL: Documentation, https://astrazeneca.github.io/magnus-core/
Project-URL: Repository, https://github.com/AstraZeneca/magnus-core
